pipeMT/__init__.py
pipeMT/async_handle.py
pipeMT/batch.py
pipeMT/device.py
pipeMT/pipeMT.py
pipeMT/profile.py
pipeMT/run.py
pipeMT/scheduler.py
pipeMT/timer.py
pipeMT/transfer.py
pipeMT/utils.py
pipemt-0.1.2.dist-info/licenses/LICENSE
pipemt-0.1.2.dist-info/METADATA
pipemt-0.1.2.dist-info/WHEEL
pipemt-0.1.2.dist-info/top_level.txt
pipemt-0.1.2.dist-info/RECORD
