Metadata-Version: 2.4
Name: pipeMT
Version: 0.1.2
Summary: Pipeline training framework for multiple large pytorch models on multiple devices
Home-page: https://github.com/ITcarrot/pipeMT
Author: ITcarrot
Author-email: luoyb9@mail2.sysu.edu.cn
License: MIT  # 例如 MIT、Apache-2.0 等
Classifier: Programming Language :: Python :: 3
Classifier: License :: OSI Approved :: MIT License
Classifier: Operating System :: OS Independent
Requires-Python: >=3.6
License-File: LICENSE
Dynamic: license-file
